micro_framework/__init__.py
micro_framework/apps.py
micro_framework/helpers.py
micro_framework/settings.py
micro_framework/jwt_auth/__init__.py
micro_framework/jwt_auth/acls.py
micro_framework/jwt_auth/admin.py
micro_framework/jwt_auth/apps.py
micro_framework/jwt_auth/authentication.py
micro_framework/jwt_auth/backends.py
micro_framework/jwt_auth/compat.py
micro_framework/jwt_auth/exceptions.py
micro_framework/jwt_auth/mixins.py
micro_framework/jwt_auth/models.py
micro_framework/jwt_auth/serializers.py
micro_framework/jwt_auth/state.py
micro_framework/jwt_auth/tokens.py
micro_framework/jwt_auth/utils.py
micro_framework/jwt_auth/views.py
micro_framework/jwt_auth/management/__init__.py
micro_framework/jwt_auth/management/commands/__init__.py
micro_framework/jwt_auth/management/commands/create_policy.py
micro_framework/jwt_auth/management/commands/delete_policy.py
micro_framework/jwt_auth/migrations/0001_initial.py
micro_framework/jwt_auth/migrations/__init__.py
micro_framework/jwt_auth/redis_token/__init__.py
micro_framework/jwt_auth/redis_token/apps.py
micro_framework/jwt_auth/redis_token/token_manager.py
micro_framework/jwt_auth/redis_token/management/__init__.py
micro_framework/jwt_auth/redis_token/management/commands/__init__.py
micro_framework/jwt_auth/redis_token/management/commands/revoke_access_redis_token.py
micro_framework/jwt_auth/redis_token/management/commands/revoke_redis_token.py
micro_framework/jwt_auth/redis_token/management/commands/revoke_refresh_redis_token.py
micro_framework/store/__init__.py
micro_framework/store/redis_backend/__init__.py
micro_framework/store/redis_backend/client.py
micro_framework/store/redis_backend/utils.py
djangomicroframework-0.0.2a5.dist-info/LICENSE
djangomicroframework-0.0.2a5.dist-info/METADATA
djangomicroframework-0.0.2a5.dist-info/WHEEL
djangomicroframework-0.0.2a5.dist-info/top_level.txt
djangomicroframework-0.0.2a5.dist-info/RECORD
