Metadata-Version: 2.1
Name: djangomicroframework
Version: 0.0.2a5
Summary: Micro framework for Django
Home-page: https://github.com/lacoski/django-micro-framework
Author: thanhnb
Author-email: bathanhtlu@gmail.com
License: MIT
Platform: UNKNOWN
Classifier: Programming Language :: Python :: 3.6
Classifier: License :: OSI Approved :: MIT License
Classifier: Operating System :: OS Independent
Requires-Python: >=3.6,<3.7
Requires-Dist: django (>=2.0)
Requires-Dist: djangorestframework (>=3.11)
Requires-Dist: hiredis (>=1.0.1)
Requires-Dist: pyjwt (>=1.7)
Requires-Dist: redis (>=3.3.11)
